{
  "$schema": "https://developer.microsoft.com/json-schemas/fabric/item/report/definition/visualContainer/2.10.0/schema.json",
  "name": "79f7cf0c7c328bd21b6b",
  "position": {
    "x": 502.85714285714289,
    "y": 0,
    "z": 1000,
    "height": 155.71428571428572,
    "width": 230.00000000000003,
    "tabOrder": 1000
  },
  "visual": {
    "visualType": "cardVisual",
    "query": {
      "queryState": {
        "Data": {
          "projections": [
            {
              "field": {
                "Measure": {
                  "Expression": {
                    "SourceRef": {
                      "Entity": "_Measures"
                    }
                  },
                  "Property": "Current Run Successful Predictions"
                }
              },
              "queryRef": "_Measures.Current Run Successful Predictions",
              "nativeQueryRef": "Successful Predictions",
              "displayName": "Successful Predictions"
            }
          ]
        }
      },
      "sortDefinition": {
        "sort": [
          {
            "field": {
              "Measure": {
                "Expression": {
                  "SourceRef": {
                    "Entity": "_Measures"
                  }
                },
                "Property": "Current Run Successful Predictions"
              }
            },
            "direction": "Descending"
          }
        ],
        "isDefaultSort": true
      }
    },
    "drillFilterOtherVisuals": true
  }
}